meshparser/__init__.py
meshparser/exceptions.py
meshparser/manipulation.py
meshparser/parser.py
meshparser/printer.py
meshparser/version.txt
meshparser/base/__init__.py
meshparser/base/parser.py
meshparser/stlparser/__init__.py
meshparser/stlparser/parser.py
meshparser/vrmlparser/__init__.py
meshparser/vrmlparser/parser.py
meshparser/vtkparser/__init__.py
meshparser/vtkparser/parser.py
meshparser-0.6.0.dist-info/LICENSE
meshparser-0.6.0.dist-info/METADATA
meshparser-0.6.0.dist-info/WHEEL
meshparser-0.6.0.dist-info/top_level.txt
meshparser-0.6.0.dist-info/zip-safe
meshparser-0.6.0.dist-info/RECORD
