Metadata-Version: 2.1
Name: meshparser
Version: 0.6.0
Summary: A Small Python library for parsing files that describe a mesh.
Home-page: https://github.com/ABI-Software/MeshParser
Author: Hugh Sorby
Author-email: h.sorby@auckland.ac.nz
License: Apache
License-File: LICENSE
Requires-Dist: pointpare
